<?xml version="1.0" encoding="utf-8"?>
<actor version="1">
  <castshadow/>
  <group>
    <variant frequency="1" name="Base">
      <mesh>skeletal/new/m_pants_loose_01.dae</mesh>
      <props>
        <prop actor="props/units/helmets/helmet_gurkhas.xml" attachpoint="helmet"/>
        <prop actor="props/units/heads/head_china.xml" attachpoint="head"/>
        <prop actor="props/units/quivers/union_rucksack.xml" attachpoint="back"/>
        <prop actor="props/units/quivers/union_belt.xml" attachpoint="sheath_L"/>
        <prop actor="props/units/weapons/rifle_idle.xml"  attachpoint="back" maxheight="-1" minheight="-1"/>
        <prop actor="props/units/weapons/longsword_mauryan.xml" attachpoint="weapon_R"/>
      </props>
      <textures>
        <texture file="skeletal/uk_uniform_infantry_pc.png" name="baseTex"/>
        <texture file="default_norm.png" name="normTex"/>
        <texture file="null_black.dds" name="specTex"/>
      </textures>
    </variant>
  </group>
  <group>
    <variant file="biped/base_swordsman_shield_relax.xml"/>
    <variant file="biped/attack_capture.xml"/>
    <variant file="biped/attack_slaughter.xml"/>
    <variant file="biped/gather_praise.xml"/>
    <variant file="biped/death_infantry.xml"/>
  </group>
  <group>
    <variant frequency="1" name="Idle"/>
  </group>
  <material>player_trans_norm_spec.xml</material>
</actor>

